README.rst
setup.py
py_nsapi/__init__.py
py_nsapi/prijzen.py
py_nsapi/reisadviezen.py
py_nsapi/stationslijst.py
py_nsapi/storingen.py
py_nsapi/trains.py
py_nsapi/vertrektijden.py
py_nsapi.egg-info/PKG-INFO
py_nsapi.egg-info/SOURCES.txt
py_nsapi.egg-info/dependency_links.txt
py_nsapi.egg-info/not-zip-safe
py_nsapi.egg-info/requires.txt
py_nsapi.egg-info/top_level.txt