Metadata-Version: 1.1
Name: py-nsapi
Version: 0.9.1
Summary: Python3 NS Train api script
Home-page: https://bitbucket.org/tvdsluijs/py-nsapi
Author: Theodorus van der Sluijs
Author-email: theo@vandersluijs.nl
License: CC BY-NC-SA 4.0
Keywords: trains transport train dutch ns
Platform: UNKNOWN
Classifier: Programming Language :: Python :: 3
Classifier: Programming Language :: Python :: 3.3
Classifier: Programming Language :: Python :: 3.4
Classifier: Programming Language :: Python :: 3.5
